izaber_zerp/__init__.py
izaber_zerp/crm.py
izaber_zerp/gui.py
izaber_zerp/product.py
izaber_zerp/timesheet.py
izaber_zerp-2.0.20230531.dist-info/METADATA
izaber_zerp-2.0.20230531.dist-info/WHEEL
izaber_zerp-2.0.20230531.dist-info/RECORD
